setup.py
fastdotcom/__init__.py
fastdotcom_test.egg-info/PKG-INFO
fastdotcom_test.egg-info/SOURCES.txt
fastdotcom_test.egg-info/dependency_links.txt
fastdotcom_test.egg-info/requires.txt
fastdotcom_test.egg-info/top_level.txt
fastdotcom_test.egg-info/zip-safe