Metadata-Version: 1.0
Name: fastdotcom-test
Version: 0.0.1
Summary: Python API for testing internet speed on Fast.com
Home-page: https://github.com/nkgilley/fast.com
Author: Nolan Gilley
Author-email: UNKNOWN
License: MIT
Platform: UNKNOWN
